VIF_PACKAGE/VIF.py
VIF_PACKAGE/__init__.py
VIF_pkg_sharad28-0.0.1.dist-info/LICENSE
VIF_pkg_sharad28-0.0.1.dist-info/METADATA
VIF_pkg_sharad28-0.0.1.dist-info/WHEEL
VIF_pkg_sharad28-0.0.1.dist-info/top_level.txt
VIF_pkg_sharad28-0.0.1.dist-info/RECORD
