Metadata-Version: 2.1
Name: VIF-pkg-sharad28
Version: 0.0.1
Summary: Calculate variance inflation factor
Home-page: https://github.com/sharad28/VIF_FACTOR
Author: Sarad Mishra
Author-email: saradmishra28@gmail.com
License: UNKNOWN
Project-URL: Bug Tracker, https://github.com/sharad28/VIF_FACTOR/issues
Platform: UNKNOWN
Classifier: Programming Language :: Python :: 3
Classifier: License :: OSI Approved :: MIT License
Classifier: Operating System :: OS Independent
Requires-Python: >=3.6
License-File: LICENSE
